odoo/addons/website_sale_stock_provisioning_date/README.rst
odoo/addons/website_sale_stock_provisioning_date/__init__.py
odoo/addons/website_sale_stock_provisioning_date/__manifest__.py
odoo/addons/website_sale_stock_provisioning_date/i18n/es.po
odoo/addons/website_sale_stock_provisioning_date/i18n/it.po
odoo/addons/website_sale_stock_provisioning_date/i18n/website_sale_stock_provisioning_date.pot
odoo/addons/website_sale_stock_provisioning_date/models/__init__.py
odoo/addons/website_sale_stock_provisioning_date/models/product_product.py
odoo/addons/website_sale_stock_provisioning_date/models/product_template.py
odoo/addons/website_sale_stock_provisioning_date/readme/CONTRIBUTORS.md
odoo/addons/website_sale_stock_provisioning_date/readme/DESCRIPTION.md
odoo/addons/website_sale_stock_provisioning_date/readme/USAGE.md
odoo/addons/website_sale_stock_provisioning_date/static/description/icon.png
odoo/addons/website_sale_stock_provisioning_date/static/description/index.html
odoo/addons/website_sale_stock_provisioning_date/static/src/js/website_sale_stock_provisioning_date_tour.esm.js
odoo/addons/website_sale_stock_provisioning_date/static/src/xml/website_sale_stock_product_availability.xml
odoo/addons/website_sale_stock_provisioning_date/tests/__init__.py
odoo/addons/website_sale_stock_provisioning_date/tests/test_website_sale_stock_provisioning_date.py
odoo/addons/website_sale_stock_provisioning_date/views/product_template_views.xml
odoo_addon_website_sale_stock_provisioning_date-18.0.1.0.0.2.dist-info/METADATA
odoo_addon_website_sale_stock_provisioning_date-18.0.1.0.0.2.dist-info/WHEEL
odoo_addon_website_sale_stock_provisioning_date-18.0.1.0.0.2.dist-info/top_level.txt
odoo_addon_website_sale_stock_provisioning_date-18.0.1.0.0.2.dist-info/RECORD
